django_tailwind_cli/__init__.py
django_tailwind_cli/apps.py
django_tailwind_cli/config.py
django_tailwind_cli/py.typed
django_tailwind_cli/management/__init__.py
django_tailwind_cli/management/commands/__init__.py
django_tailwind_cli/management/commands/tailwind.py
django_tailwind_cli/templates/tailwind_cli/base.html
django_tailwind_cli/templates/tailwind_cli/tailwind_css.html
django_tailwind_cli/templatetags/__init__.py
django_tailwind_cli/templatetags/tailwind_cli.py
django_tailwind_cli/utils/__init__.py
django_tailwind_cli/utils/http.py
django_tailwind_cli-4.5.1.dist-info/METADATA
django_tailwind_cli-4.5.1.dist-info/WHEEL
django_tailwind_cli-4.5.1.dist-info/licenses/LICENSE
django_tailwind_cli-4.5.1.dist-info/RECORD
