Metadata-Version: 2.4
Name: django-tailwind-cli
Version: 4.5.1
Summary: Django and Tailwind integration based on the prebuilt Tailwind CSS CLI.
Project-URL: Home, https://django-tailwind-cli.rtfd.io/
Project-URL: Documentation, https://django-tailwind-cli.rtfd.io/
Project-URL: Repository, https://github.com/django-commons/django-tailwind-cli
Author-email: Oliver Andrich <oliver@andrich.me>
License: MIT License
License-File: LICENSE
Keywords: css,django,tailwind
Classifier: Development Status :: 5 - Production/Stable
Classifier: Environment :: Web Environment
Classifier: Framework :: Django :: 4.2
Classifier: Framework :: Django :: 5.2
Classifier: Framework :: Django :: 6.0
Classifier: Intended Audience :: Developers
Classifier: License :: OSI Approved :: MIT License
Classifier: Operating System :: OS Independent
Classifier: Programming Language :: Python :: 3.10
Classifier: Programming Language :: Python :: 3.11
Classifier: Programming Language :: Python :: 3.12
Classifier: Programming Language :: Python :: 3.13
Classifier: Programming Language :: Python :: 3.14
Classifier: Topic :: Software Development :: Libraries
Classifier: Topic :: Utilities
Requires-Python: >=3.10
Requires-Dist: django!=5.0.*,!=5.1.*,>=4.2
Requires-Dist: django-typer>=2.1.2
Requires-Dist: semver>=3.0.4
Provides-Extra: django-extensions
Requires-Dist: django-extensions>=3.2; extra == 'django-extensions'
Requires-Dist: werkzeug>=3.0; extra == 'django-extensions'
